{"tenantId": "kl","moduleName": "TradeLicense","TradeReg": [{
    "name": "Establishment/Installation Permit for Industries, Factories, Workshop and Powered Machineries",
    "code": "TR1",
    "active": "true",
    "type": "TL",
    "validityPeriod": null
},{
    "name": "IFTE & OS License Service",
    "code": "TR2",
    "active": "true",
    "type": "TL",
    "validityPeriod": null
},{
    "name": "Livestock/Pets\u00a0Related\u00a0Licenses & Permits",
    "code": "TR3",
    "active": "true",
    "type": "TL",
    "validityPeriod": null
},{
    "name": "Application for Registration and fee remittance of Industrial unit in Industrial Estate/Industrial Park/SEZ",
    "code": "TR4",
    "active": "true",
    "type": "TL",
    "validityPeriod": null
},{
    "name": "Registration & License for Private Hospitals and Para Medical Institutions",
    "code": "TR5",
    "active": "true",
    "type": "TL",
    "validityPeriod": null
},{
    "name": "Registration & License of Tutorial Institutions",
    "code": "TR6",
    "active": "true",
    "type": "TL",
    "validityPeriod": null
},{
    "name": "License for Cinematograph Exhibition",
    "code": "TR7",
    "active": "true",
    "type": "TL",
    "validityPeriod": null
},{
    "name": "PPR License",
    "code": "TR8",
    "active": "true",
    "type": "TL",
    "validityPeriod": null
},{
    "name": "Licenses for Private Places for Public Purposes - Market/Parking/Burial Places",
    "code": "TR9",
    "active": "true",
    "type": "TL",
    "validityPeriod": null
},{
    "name": "License, Numbering & Taxing of Water Vessels",
    "code": "TR10",
    "active": "true",
    "type": "TL",
    "validityPeriod": null
},{
    "name": "Street Vending - Vending Zones & Vender's ID and Vending License",
    "code": "TR11",
    "active": "true",
    "type": "TL",
    "validityPeriod": null
},{
    "name": "Street Vending - Vending Zones & Vender's ID and Vending License",
    "code": "TR11",
    "active": "true",
    "type": "TL",
    "validityPeriod": null
}]}