{
  "tenantId": "kl",
  "moduleName": "birth-death-service",
  "WorkFlowMarriage": [
    {
      "tenantId": "kl",
      "ApplicationType": "CRMRNR",
      "BusinessService": "CR",
      "WorkflowCode": "MARRIAGE45DYS",
      "startdateperiod": 0,
      "enddateperiod": 3888000000,
      "payment": false,
      "amount": 100,
      "scstamount":10,
      "active": true
    },
    {
      "tenantId": "kl",
      "ApplicationType": "CRMRNR",
      "BusinessService": "CR",
      "WorkflowCode": "MARRIAGE5YEARS",
      "startdateperiod": 3888000000,
      "enddateperiod": 157680000000,
      "payment": false,
      "amount": 200,
      "scstamount":10,
      "active": true
    },
    {
      "tenantId": "kl",
      "ApplicationType": "CRMRNR",
      "BusinessService": "CR",
      "WorkflowCode": "MARRIAGEABOVE5YEARS",
      "startdateperiod": 157680000000,
      "enddateperiod": 31449600000000,
      "payment": false,
      "amount": 350,
      "scstamount":10,
      "active": true
    },
     {
      "tenantId": "kl",
      "ApplicationType": "CRMRIC",
      "BusinessService": "CR",
      "WorkflowCode": "CORRECTIONMARRIAGE",
      "startdateperiod": 0,
      "enddateperiod": 0,
      "payment": false,
      "amount": 100,
      "active": true
    }
   
     
  ]
}
